[
    {
        "hash": "4a54923f15c9642dd449c43f928acac1", 
        "significance_raw": 0.7262178301003318, 
        "significance_scaled": -1, 
        "significance_weighted": 0.6194944865873097, 
        "yield_raw": {
            "bkg": 220.0, 
            "sig": 66.0
        }, 
        "yield_scaled": {
            "bkg": 5.652214944856574, 
            "sig": 0.008998775453791151
        }, 
        "yield_weighted": {
            "bkg": 251.22697365229672, 
            "sig": 66.0
        }
    }, 
    {
        "hash": "76edc6489a3dbef60ace24dd241558e6", 
        "significance_raw": 2.07234617707586, 
        "significance_scaled": -1, 
        "significance_weighted": 1.7767158872395994, 
        "yield_raw": {
            "bkg": 78.0, 
            "sig": 65.0
        }, 
        "yield_scaled": {
            "bkg": 0.4706156781980367, 
            "sig": 0.008862430371157953
        }, 
        "yield_weighted": {
            "bkg": 92.06956078263993, 
            "sig": 65.0
        }
    }, 
    {
        "hash": "c9e65a7247173700a6f40dd6260749f7", 
        "significance_raw": 0.9184706841782373, 
        "significance_scaled": -1, 
        "significance_weighted": 0.7923686928875187, 
        "yield_raw": {
            "bkg": 187.0, 
            "sig": 69.0
        }, 
        "yield_scaled": {
            "bkg": 1.762995801218474, 
            "sig": 0.009407810701690748
        }, 
        "yield_weighted": {
            "bkg": 213.31025876289615, 
            "sig": 69.0
        }
    }, 
    {
        "hash": "c2a1fe83da7f80c3aee22ce00e92167e", 
        "significance_raw": 0.8254914576976643, 
        "significance_scaled": -1, 
        "significance_weighted": 0.7198746356411327, 
        "yield_raw": {
            "bkg": 167.0, 
            "sig": 56.0
        }, 
        "yield_scaled": {
            "bkg": 0.9993076693968, 
            "sig": 0.007635324627459158
        }, 
        "yield_weighted": {
            "bkg": 188.06856921709425, 
            "sig": 56.0
        }
    }, 
    {
        "hash": "a96d84222f842541ebe92898b1df9f5a", 
        "significance_raw": 3.818079349782647, 
        "significance_scaled": -1, 
        "significance_weighted": 3.3626043290933323, 
        "yield_raw": {
            "bkg": 48.0, 
            "sig": 82.0
        }, 
        "yield_scaled": {
            "bkg": 0.2491195797728461, 
            "sig": 0.01118029677592234
        }, 
        "yield_weighted": {
            "bkg": 56.190667125311506, 
            "sig": 82.0
        }
    }, 
    {
        "hash": "e9c739682705286351b127b50d91dc55", 
        "significance_raw": 0.5930434098668587, 
        "significance_scaled": -1, 
        "significance_weighted": 0.40971197608229215, 
        "yield_raw": {
            "bkg": 489.0, 
            "sig": 124.0
        }, 
        "yield_scaled": {
            "bkg": 7.695669535582787, 
            "sig": 0.016906790246516708
        }, 
        "yield_weighted": {
            "bkg": 647.5830535181683, 
            "sig": 124.0
        }
    }, 
    {
        "hash": "59ae118087809de506dca384f01a05ec", 
        "significance_raw": 0.6345923376008092, 
        "significance_scaled": -1, 
        "significance_weighted": 0.5253682058345851, 
        "yield_raw": {
            "bkg": 209.0, 
            "sig": 56.0
        }, 
        "yield_scaled": {
            "bkg": 6.254401615815154, 
            "sig": 0.007635324627459158
        }, 
        "yield_weighted": {
            "bkg": 243.04147252817356, 
            "sig": 56.0
        }
    }, 
    {
        "hash": "1308e6e324638208abaaa8e2543cf536", 
        "significance_raw": 1.039554657104641, 
        "significance_scaled": -1, 
        "significance_weighted": 0.6072996164779313, 
        "yield_raw": {
            "bkg": 220.0, 
            "sig": 91.0
        }, 
        "yield_scaled": {
            "bkg": 2.235189264305709, 
            "sig": 0.012407402519621132
        }, 
        "yield_weighted": {
            "bkg": 352.0376538027612, 
            "sig": 91.0
        }
    }, 
    {
        "hash": "8661fce7a89358495faba21e7b7f0cda", 
        "significance_raw": 0.9269847615372826, 
        "significance_scaled": -1, 
        "significance_weighted": 0.6372819853329597, 
        "yield_raw": {
            "bkg": 344.0, 
            "sig": 128.0
        }, 
        "yield_scaled": {
            "bkg": 3.8716923501846896, 
            "sig": 0.017452170577049505
        }, 
        "yield_weighted": {
            "bkg": 476.0558491014032, 
            "sig": 128.0
        }
    }, 
    {
        "hash": "ea55557f463b337757c2164214f07634", 
        "significance_raw": 1.12305531501331, 
        "significance_scaled": -1, 
        "significance_weighted": 0.6648701151642219, 
        "yield_raw": {
            "bkg": 209.0, 
            "sig": 93.0
        }, 
        "yield_scaled": {
            "bkg": 1.7568157439510244, 
            "sig": 0.01268009268488753
        }, 
        "yield_weighted": {
            "bkg": 333.95849979681054, 
            "sig": 93.0
        }
    }, 
    {
        "hash": "9fed3bd970bcb97ad5efff74431472d5", 
        "significance_raw": 1.7666466844568403, 
        "significance_scaled": -1, 
        "significance_weighted": 1.4365474728597927, 
        "yield_raw": {
            "bkg": 57.0, 
            "sig": 40.0
        }, 
        "yield_scaled": {
            "bkg": 0.31835021760968796, 
            "sig": 0.0054538033053279705
        }, 
        "yield_weighted": {
            "bkg": 70.58883431036263, 
            "sig": 40.0
        }
    }, 
    {
        "hash": "48cee7758408285fced591869e78835b", 
        "significance_raw": 0.9967031918001489, 
        "significance_scaled": -1, 
        "significance_weighted": 0.8311540579204113, 
        "yield_raw": {
            "bkg": 88.0, 
            "sig": 35.0
        }, 
        "yield_scaled": {
            "bkg": 0.5272583254949816, 
            "sig": 0.004772077892161973
        }, 
        "yield_weighted": {
            "bkg": 103.74566564311628, 
            "sig": 35.0
        }
    }, 
    {
        "hash": "3512cb31d6d7d5b8c5c3fe12d3dc80b8", 
        "significance_raw": 1.3675375419578855, 
        "significance_scaled": -1, 
        "significance_weighted": 1.1561108909359366, 
        "yield_raw": {
            "bkg": 89.0, 
            "sig": 48.0
        }, 
        "yield_scaled": {
            "bkg": 0.6033215844794606, 
            "sig": 0.006544563966393564
        }, 
        "yield_weighted": {
            "bkg": 104.91646069201994, 
            "sig": 48.0
        }
    }, 
    {
        "hash": "b8106819c44b05f427692196c6fa7efc", 
        "significance_raw": 0.24286344544485725, 
        "significance_scaled": -1, 
        "significance_weighted": 0.21000177583725999, 
        "yield_raw": {
            "bkg": 563.0, 
            "sig": 77.0
        }, 
        "yield_scaled": {
            "bkg": 19.259911219823817, 
            "sig": 0.010498571362756342
        }, 
        "yield_weighted": {
            "bkg": 610.1830604017831, 
            "sig": 77.0
        }
    }, 
    {
        "hash": "40d5f46d2217fc1efd6da334452fdd55", 
        "significance_raw": 3.485423033532407, 
        "significance_scaled": -1, 
        "significance_weighted": 3.170124611151458, 
        "yield_raw": {
            "bkg": 40.0, 
            "sig": 61.0
        }, 
        "yield_scaled": {
            "bkg": 0.21732053721902378, 
            "sig": 0.008317050040625154
        }, 
        "yield_weighted": {
            "bkg": 44.90100095825102, 
            "sig": 61.0
        }
    }, 
    {
        "hash": "1d5fb638dc633be71ce8cde3d65a98e9", 
        "significance_raw": 1.0989888060833217, 
        "significance_scaled": -1, 
        "significance_weighted": 0.6375887410422343, 
        "yield_raw": {
            "bkg": 195.0, 
            "sig": 85.0
        }, 
        "yield_scaled": {
            "bkg": 1.4069521336835167, 
            "sig": 0.011589332023821935
        }, 
        "yield_weighted": {
            "bkg": 316.00562006126734, 
            "sig": 85.0
        }
    }, 
    {
        "hash": "8457674b02284cb5b9c8f6ff133ca095", 
        "significance_raw": 1.0495262507157386, 
        "significance_scaled": -1, 
        "significance_weighted": 0.6616488383158436, 
        "yield_raw": {
            "bkg": 242.0, 
            "sig": 101.0
        }, 
        "yield_scaled": {
            "bkg": 1.702964343866175, 
            "sig": 0.013770853345953123
        }, 
        "yield_weighted": {
            "bkg": 364.1553703198911, 
            "sig": 101.0
        }
    }, 
    {
        "hash": "a9ae1a9c86c35cf275f91e4633ac7f79", 
        "significance_raw": 0.5946834908141628, 
        "significance_scaled": -1, 
        "significance_weighted": 0.4540877292580663, 
        "yield_raw": {
            "bkg": 543.0, 
            "sig": 138.0
        }, 
        "yield_scaled": {
            "bkg": 9.09847577307775, 
            "sig": 0.018815621403381496
        }, 
        "yield_weighted": {
            "bkg": 668.860138695314, 
            "sig": 138.0
        }
    }, 
    {
        "hash": "dc8235406c72af63f179b4e9e48d4299", 
        "significance_raw": 1.2120525103229234, 
        "significance_scaled": -1, 
        "significance_weighted": 1.0450457698206237, 
        "yield_raw": {
            "bkg": 142.0, 
            "sig": 68.0
        }, 
        "yield_scaled": {
            "bkg": 1.2674309754488264, 
            "sig": 0.009271465619057548
        }, 
        "yield_weighted": {
            "bkg": 163.58593871747178, 
            "sig": 68.0
        }
    }, 
    {
        "hash": "1762a643130510182d941fd7bf60bfbd", 
        "significance_raw": 1.141404586628346, 
        "significance_scaled": -1, 
        "significance_weighted": 0.6711312894096787, 
        "yield_raw": {
            "bkg": 208.0, 
            "sig": 94.0
        }, 
        "yield_scaled": {
            "bkg": 1.8378636835879154, 
            "sig": 0.01281643776752073
        }, 
        "yield_weighted": {
            "bkg": 334.92068677169647, 
            "sig": 94.0
        }
    }, 
    {
        "hash": "82a9034e90c00aebe6068c4e46a09e06", 
        "significance_raw": 3.617828126933216, 
        "significance_scaled": -1, 
        "significance_weighted": 3.3616525387095173, 
        "yield_raw": {
            "bkg": 67.0, 
            "sig": 107.0
        }, 
        "yield_scaled": {
            "bkg": 0.4332785621884377, 
            "sig": 0.01458892384175232
        }, 
        "yield_weighted": {
            "bkg": 73.34738846198792, 
            "sig": 107.0
        }
    }, 
    {
        "hash": "f4ca7549b2c469647b6bbf1488cc0cc8", 
        "significance_raw": 1.0594219792295099, 
        "significance_scaled": -1, 
        "significance_weighted": 0.9379691004920766, 
        "yield_raw": {
            "bkg": 133.0, 
            "sig": 56.0
        }, 
        "yield_scaled": {
            "bkg": 0.8180594919066183, 
            "sig": 0.007635324627459158
        }, 
        "yield_weighted": {
            "bkg": 148.89208534754164, 
            "sig": 56.0
        }
    }, 
    {
        "hash": "ed4bbd89af1fe1c4d792a417bea33a87", 
        "significance_raw": 1.0045490545171882, 
        "significance_scaled": -1, 
        "significance_weighted": 0.7086495793814626, 
        "yield_raw": {
            "bkg": 317.0, 
            "sig": 127.0
        }, 
        "yield_scaled": {
            "bkg": 4.073214440843202, 
            "sig": 0.017315825494416306
        }, 
        "yield_weighted": {
            "bkg": 432.2486331463414, 
            "sig": 127.0
        }
    }, 
    {
        "hash": "3ee9a587e22f38a0c7d255a35dafd787", 
        "significance_raw": 0.8374377402671538, 
        "significance_scaled": -1, 
        "significance_weighted": 0.739955090622675, 
        "yield_raw": {
            "bkg": 212.0, 
            "sig": 72.0
        }, 
        "yield_scaled": {
            "bkg": 2.2704861340925313, 
            "sig": 0.009816845949590345
        }, 
        "yield_weighted": {
            "bkg": 236.18039402788776, 
            "sig": 72.0
        }
    }, 
    {
        "hash": "827407bdde08b76ef7c5063659c53f50", 
        "significance_raw": 0.3302697554362643, 
        "significance_scaled": -1, 
        "significance_weighted": 0.28349511311735826, 
        "yield_raw": {
            "bkg": 460.0, 
            "sig": 76.0
        }, 
        "yield_scaled": {
            "bkg": 15.95277475894265, 
            "sig": 0.010362226280123144
        }, 
        "yield_weighted": {
            "bkg": 506.8878540647147, 
            "sig": 76.0
        }
    }
]